torchcell/__init__.py
torchcell/__version__.py
torchcell/cell.py
torchcell/config.py
torchcell/data_download_yeastmine.py
torchcell/dataloading_lmdb.py
torchcell/delete_subset.py
torchcell/mypy_check.py
torchcell/ncbi.py
torchcell/neo4j_example.py
torchcell/neo4j_fitness_lmdb.py
torchcell/prof.py
torchcell/py.typed
torchcell/sc_graph.py
torchcell/torchcell.mplstyle
torchcell/utils.py
torchcell/adapters/__init__.py
torchcell/adapters/cell_adapter.py
torchcell/adapters/costanzo2016_adapter.py
torchcell/adapters/kuzmin2018_adapter.py
torchcell/adapters/kuzmin2020_adapter.py
torchcell/adapters/sgd_adapter.py
torchcell/adapters/synth_leth_db_adapter.py
torchcell/adapters/conf/__init__.py
torchcell/adapters/conf/default.yaml
torchcell/adapters/conf/dmf_costanzo2016_adapter.yaml
torchcell/adapters/conf/dmf_kuzmin2018_adapter.yaml
torchcell/adapters/conf/dmf_kuzmin2020_adapter.yaml
torchcell/adapters/conf/dmi_costanzo2016_adapter.yaml
torchcell/adapters/conf/dmi_kuzmin2018_adapter.yaml
torchcell/adapters/conf/dmi_kuzmin2020_adapter.yaml
torchcell/adapters/conf/gene_essentiality_sgd_adapter.yaml
torchcell/adapters/conf/smf_costanzo2016_adapter.yaml
torchcell/adapters/conf/smf_kuzmin2018_adapter.yaml
torchcell/adapters/conf/smf_kuzmin2020_adapter.yaml
torchcell/adapters/conf/synth_lethality_yeast_synth_leth_db_adapter.yaml
torchcell/adapters/conf/synth_rescue_yeast_synth_leth_db_adapter.yaml
torchcell/adapters/conf/tmf_kuzmin2018_adapter.yaml
torchcell/adapters/conf/tmf_kuzmin2020_adapter.yaml
torchcell/adapters/conf/tmi_kuzmin2018_adapter.yaml
torchcell/adapters/conf/tmi_kuzmin2020_adapter.yaml
torchcell/cell/__init__.py
torchcell/data/__init__.py
torchcell/data/data.py
torchcell/data/embedding.py
torchcell/data/experiment_dataset.py
torchcell/data/neo4j_cell.py
torchcell/data/neo4j_query_raw.py
torchcell/database/__init__.py
torchcell/database/biocypher_out_combine.py
torchcell/database/build_command.py
torchcell/database/directory_setup.py
torchcell/database/tcdb.py
torchcell-0.2.8.dist-info/METADATA
torchcell-0.2.8.dist-info/WHEEL
torchcell-0.2.8.dist-info/entry_points.txt
torchcell-0.2.8.dist-info/top_level.txt
torchcell-0.2.8.dist-info/RECORD
